{"_ts":[1569977350,1570151747,1570325450,1570587598,1571024124,1571199404,1571635908],"_r":{"breakdown":{"html":{"bytes":[0,0,0,0,0,0,0],"requests":[0,0,0,0,0,0,0]},"js":{"bytes":[0,0,0,0,0,0,0],"requests":[0,0,0,0,0,0,0]},"css":{"bytes":[0,0,0,0,0,0,0],"requests":[0,0,0,0,0,0,0]},"image":{"bytes":[0,0,0,0,0,0,0],"requests":[0,0,0,0,0,0,0]},"flash":{"bytes":[0,0,0,0,0,0,0],"requests":[0,0,0,0,0,0,0]},"font":{"bytes":[0,0,0,0,0,0,0],"requests":[0,0,0,0,0,0,0]},"video":{"bytes":[0,0,0,0,0,0,0],"requests":[0,0,0,0,0,0,0]},"other":{"bytes":[0,0,0,0,0,0,0],"requests":[0,0,0,0,0,0,0]}},"date":[1569977350,1570151747,1570325450,1570587598,1571024124,1571199404,1571635908],"domElements":[null,null,null,null,null,null,null],"domInteractive":[0,0,0,0,0,0,0],"firstPaint":[0,0,0,0,0,0,0],"fullyLoaded":[0,0,0,0,0,0,0],"id":["191002_BG_6549b727189ced96226d3680af5734b3","191004_0B_b76a79774b3a0edc95df6db008045acd","191006_K3_febba17f1900807f4847daa43438628e","191009_ZJ_a5549747abb9a105c3eff095395f027c","191014_15_11265cac29fc356f04105697d54ef1f7","191016_FQ_b53822f161dd7492c09f006b0e720b6a","191021_G1_8616caef4b82c5df9a3b41a7dfff7022"],"loadTime":[0,0,0,0,0,0,0],"render":[0,0,0,0,0,0,0],"SpeedIndex":[0,0,0,0,0,0,0],"TTFB":[0,0,0,0,0,0,0],"videoFrames":[[{"_i":"ms_000000.jpg","_t":0,"_vc":100}],[{"_i":"ms_000000.jpg","_t":0,"_vc":100}],[{"_i":"ms_000000.jpg","_t":0,"_vc":100}],[{"_i":"ms_000000.jpg","_t":0,"_vc":100}],[{"_i":"ms_000000.jpg","_t":0,"_vc":100}],[{"_i":"ms_000000.jpg","_t":0,"_vc":100}],[{"_i":"ms_000000.jpg","_t":0,"_vc":100}]],"visualComplete":[0,0,0,0,0,0,0],"lighthouse":[null,null,null,null,null,null,null],"pagespeed":[54,54,null,null,null,null,null]}}