{"_ts":[1543627217,1543714085],"_r":{"breakdown":{"html":{"bytes":[59249,59221],"requests":[13,13]},"js":{"bytes":[388345,388315],"requests":[16,16]},"css":{"bytes":[26858,26858],"requests":[2,2]},"image":{"bytes":[446311,446226],"requests":[23,23]},"flash":{"bytes":[0,0],"requests":[0,0]},"font":{"bytes":[114144,114144],"requests":[6,6]},"video":{"bytes":[0,0],"requests":[0,0]},"other":{"bytes":[1055,1048],"requests":[2,3]}},"date":[1543627217,1543714085],"domElements":[873,873],"domInteractive":[4479,5599],"firstPaint":[3283.2000000053,4666.2999999971],"fullyLoaded":[16409,18654],"id":["181201_2X_e4301baecce848097547d245d2218a5a","181202_CA_73807393f4b6f5662fc35036722607ae"],"loadTime":[16409,18654],"render":[3712,5133],"SpeedIndex":[11972,14166],"TTFB":[1864,1841],"videoFrames":[[{"_i":"ms_000000.jpg","_t":0,"_vc":0},{"_i":"ms_003712.jpg","_t":3712,"_vc":9},{"_i":"ms_003745.jpg","_t":3745,"_vc":9},{"_i":"ms_003782.jpg","_t":3782,"_vc":9},{"_i":"ms_003801.jpg","_t":3801,"_vc":9},{"_i":"ms_003819.jpg","_t":3819,"_vc":9},{"_i":"ms_003854.jpg","_t":3854,"_vc":8},{"_i":"ms_003889.jpg","_t":3889,"_vc":8},{"_i":"ms_003909.jpg","_t":3909,"_vc":8},{"_i":"ms_003939.jpg","_t":3939,"_vc":8},{"_i":"ms_004038.jpg","_t":4038,"_vc":12},{"_i":"ms_004768.jpg","_t":4768,"_vc":27},{"_i":"ms_004811.jpg","_t":4811,"_vc":26},{"_i":"ms_004905.jpg","_t":4905,"_vc":26},{"_i":"ms_005000.jpg","_t":5000,"_vc":25},{"_i":"ms_005115.jpg","_t":5115,"_vc":33},{"_i":"ms_005214.jpg","_t":5214,"_vc":33},{"_i":"ms_005318.jpg","_t":5318,"_vc":34},{"_i":"ms_005409.jpg","_t":5409,"_vc":34},{"_i":"ms_005515.jpg","_t":5515,"_vc":34},{"_i":"ms_005604.jpg","_t":5604,"_vc":34},{"_i":"ms_005722.jpg","_t":5722,"_vc":29},{"_i":"ms_005811.jpg","_t":5811,"_vc":30},{"_i":"ms_005927.jpg","_t":5927,"_vc":30},{"_i":"ms_006030.jpg","_t":6030,"_vc":30},{"_i":"ms_006107.jpg","_t":6107,"_vc":30},{"_i":"ms_006208.jpg","_t":6208,"_vc":32},{"_i":"ms_006300.jpg","_t":6300,"_vc":31},{"_i":"ms_006424.jpg","_t":6424,"_vc":31},{"_i":"ms_006517.jpg","_t":6517,"_vc":31},{"_i":"ms_006612.jpg","_t":6612,"_vc":31},{"_i":"ms_006717.jpg","_t":6717,"_vc":31},{"_i":"ms_006800.jpg","_t":6800,"_vc":30},{"_i":"ms_006912.jpg","_t":6912,"_vc":31},{"_i":"ms_007012.jpg","_t":7012,"_vc":30},{"_i":"ms_007109.jpg","_t":7109,"_vc":31},{"_i":"ms_007217.jpg","_t":7217,"_vc":30},{"_i":"ms_007343.jpg","_t":7343,"_vc":30},{"_i":"ms_011976.jpg","_t":11976,"_vc":33},{"_i":"ms_012036.jpg","_t":12036,"_vc":33},{"_i":"ms_012112.jpg","_t":12112,"_vc":32},{"_i":"ms_012213.jpg","_t":12213,"_vc":32},{"_i":"ms_015045.jpg","_t":15045,"_vc":85},{"_i":"ms_016409.jpg","_t":16409,"_vc":100}],[{"_i":"ms_000000.jpg","_t":0,"_vc":0},{"_i":"ms_005133.jpg","_t":5133,"_vc":10},{"_i":"ms_005161.jpg","_t":5161,"_vc":12},{"_i":"ms_005181.jpg","_t":5181,"_vc":12},{"_i":"ms_005216.jpg","_t":5216,"_vc":12},{"_i":"ms_005234.jpg","_t":5234,"_vc":12},{"_i":"ms_005253.jpg","_t":5253,"_vc":12},{"_i":"ms_005270.jpg","_t":5270,"_vc":12},{"_i":"ms_005288.jpg","_t":5288,"_vc":12},{"_i":"ms_005305.jpg","_t":5305,"_vc":12},{"_i":"ms_005517.jpg","_t":5517,"_vc":12},{"_i":"ms_005770.jpg","_t":5770,"_vc":26},{"_i":"ms_005811.jpg","_t":5811,"_vc":24},{"_i":"ms_005915.jpg","_t":5915,"_vc":24},{"_i":"ms_006010.jpg","_t":6010,"_vc":24},{"_i":"ms_006116.jpg","_t":6116,"_vc":24},{"_i":"ms_006218.jpg","_t":6218,"_vc":24},{"_i":"ms_006310.jpg","_t":6310,"_vc":30},{"_i":"ms_006415.jpg","_t":6415,"_vc":30},{"_i":"ms_006523.jpg","_t":6523,"_vc":36},{"_i":"ms_006609.jpg","_t":6609,"_vc":36},{"_i":"ms_006709.jpg","_t":6709,"_vc":29},{"_i":"ms_006813.jpg","_t":6813,"_vc":29},{"_i":"ms_006900.jpg","_t":6900,"_vc":29},{"_i":"ms_007005.jpg","_t":7005,"_vc":29},{"_i":"ms_007138.jpg","_t":7138,"_vc":29},{"_i":"ms_007210.jpg","_t":7210,"_vc":31},{"_i":"ms_007327.jpg","_t":7327,"_vc":31},{"_i":"ms_007424.jpg","_t":7424,"_vc":31},{"_i":"ms_007510.jpg","_t":7510,"_vc":30},{"_i":"ms_007601.jpg","_t":7601,"_vc":30},{"_i":"ms_007713.jpg","_t":7713,"_vc":31},{"_i":"ms_007803.jpg","_t":7803,"_vc":31},{"_i":"ms_007904.jpg","_t":7904,"_vc":30},{"_i":"ms_008001.jpg","_t":8001,"_vc":31},{"_i":"ms_008107.jpg","_t":8107,"_vc":31},{"_i":"ms_008209.jpg","_t":8209,"_vc":31},{"_i":"ms_008316.jpg","_t":8316,"_vc":31},{"_i":"ms_008410.jpg","_t":8410,"_vc":30},{"_i":"ms_008541.jpg","_t":8541,"_vc":30},{"_i":"ms_008615.jpg","_t":8615,"_vc":30},{"_i":"ms_008708.jpg","_t":8708,"_vc":30},{"_i":"ms_014186.jpg","_t":14186,"_vc":33},{"_i":"ms_014274.jpg","_t":14274,"_vc":33},{"_i":"ms_014322.jpg","_t":14322,"_vc":32},{"_i":"ms_014402.jpg","_t":14402,"_vc":32},{"_i":"ms_014518.jpg","_t":14518,"_vc":31},{"_i":"ms_017703.jpg","_t":17703,"_vc":85},{"_i":"ms_018654.jpg","_t":18654,"_vc":100}]],"visualComplete":[16409,18654],"lighthouse":[35,35],"pagespeed":[62,62]}}