{"_ts":[1530423066,1530510312,1530597210],"_r":{"breakdown":{"html":{"bytes":[59098,60591,59090],"requests":[22,25,22]},"js":{"bytes":[368175,368190,368204],"requests":[17,17,17]},"css":{"bytes":[6144,6144,6144],"requests":[1,1,1]},"image":{"bytes":[513984,716372,751700],"requests":[25,28,25]},"flash":{"bytes":[0,0,0],"requests":[0,0,0]},"font":{"bytes":[113746,113746,113746],"requests":[6,6,6]},"video":{"bytes":[0,0,0],"requests":[0,0,0]},"other":{"bytes":[506,506,507],"requests":[5,5,5]}},"date":[1530423066,1530510312,1530597210],"domElements":[994,1027,994],"domInteractive":[2160,2487,2299],"firstPaint":[1301.9000031054,1537.8000000492,1282.300000079],"fullyLoaded":[7732,5848,5127],"id":["180701_99_05112c8bafafb96ebf07f3e95fc220ba","180702_PJ_a7e2a1dbd5c5ee7f1175debca1967324","180703_GW_25402192026d202c405ff4e34d5a3ed4"],"loadTime":[4810,5518,5127],"render":[1799,1987,1844],"SpeedIndex":[2964,3603,3503],"TTFB":[403,669,531],"videoFrames":[[{"_i":"ms_000000.jpg","_t":0,"_vc":0},{"_i":"ms_001799.jpg","_t":1799,"_vc":17},{"_i":"ms_001845.jpg","_t":1845,"_vc":12},{"_i":"ms_001946.jpg","_t":1946,"_vc":41},{"_i":"ms_002002.jpg","_t":2002,"_vc":42},{"_i":"ms_002432.jpg","_t":2432,"_vc":56},{"_i":"ms_002450.jpg","_t":2450,"_vc":56},{"_i":"ms_002467.jpg","_t":2467,"_vc":56},{"_i":"ms_002485.jpg","_t":2485,"_vc":56},{"_i":"ms_002504.jpg","_t":2504,"_vc":56},{"_i":"ms_002600.jpg","_t":2600,"_vc":56},{"_i":"ms_002708.jpg","_t":2708,"_vc":56},{"_i":"ms_002818.jpg","_t":2818,"_vc":56},{"_i":"ms_002915.jpg","_t":2915,"_vc":56},{"_i":"ms_003035.jpg","_t":3035,"_vc":55},{"_i":"ms_003132.jpg","_t":3132,"_vc":55},{"_i":"ms_003208.jpg","_t":3208,"_vc":54},{"_i":"ms_003303.jpg","_t":3303,"_vc":49},{"_i":"ms_003401.jpg","_t":3401,"_vc":49},{"_i":"ms_003512.jpg","_t":3512,"_vc":50},{"_i":"ms_003619.jpg","_t":3619,"_vc":44},{"_i":"ms_003704.jpg","_t":3704,"_vc":60},{"_i":"ms_003886.jpg","_t":3886,"_vc":62},{"_i":"ms_003904.jpg","_t":3904,"_vc":62},{"_i":"ms_004036.jpg","_t":4036,"_vc":86},{"_i":"ms_004119.jpg","_t":4119,"_vc":94},{"_i":"ms_004352.jpg","_t":4352,"_vc":98},{"_i":"ms_004411.jpg","_t":4411,"_vc":98},{"_i":"ms_004514.jpg","_t":4514,"_vc":99},{"_i":"ms_004613.jpg","_t":4613,"_vc":99},{"_i":"ms_004724.jpg","_t":4724,"_vc":99},{"_i":"ms_004810.jpg","_t":4810,"_vc":100},{"_i":"ms_004922.jpg","_t":4922,"_vc":100},{"_i":"ms_005006.jpg","_t":5006,"_vc":100},{"_i":"ms_005102.jpg","_t":5102,"_vc":100},{"_i":"ms_005233.jpg","_t":5233,"_vc":100},{"_i":"ms_006308.jpg","_t":6308,"_vc":100},{"_i":"ms_007732.jpg","_t":7732,"_vc":100}],[{"_i":"ms_000000.jpg","_t":0,"_vc":0},{"_i":"ms_001987.jpg","_t":1987,"_vc":7},{"_i":"ms_002116.jpg","_t":2116,"_vc":48},{"_i":"ms_002179.jpg","_t":2179,"_vc":37},{"_i":"ms_002346.jpg","_t":2346,"_vc":37},{"_i":"ms_002711.jpg","_t":2711,"_vc":48},{"_i":"ms_002731.jpg","_t":2731,"_vc":48},{"_i":"ms_002998.jpg","_t":2998,"_vc":48},{"_i":"ms_003042.jpg","_t":3042,"_vc":48},{"_i":"ms_003065.jpg","_t":3065,"_vc":48},{"_i":"ms_003107.jpg","_t":3107,"_vc":48},{"_i":"ms_003212.jpg","_t":3212,"_vc":48},{"_i":"ms_003307.jpg","_t":3307,"_vc":48},{"_i":"ms_003408.jpg","_t":3408,"_vc":48},{"_i":"ms_003511.jpg","_t":3511,"_vc":47},{"_i":"ms_003640.jpg","_t":3640,"_vc":47},{"_i":"ms_003702.jpg","_t":3702,"_vc":47},{"_i":"ms_003813.jpg","_t":3813,"_vc":47},{"_i":"ms_003908.jpg","_t":3908,"_vc":47},{"_i":"ms_004038.jpg","_t":4038,"_vc":47},{"_i":"ms_004108.jpg","_t":4108,"_vc":28},{"_i":"ms_004226.jpg","_t":4226,"_vc":52},{"_i":"ms_004307.jpg","_t":4307,"_vc":51},{"_i":"ms_004402.jpg","_t":4402,"_vc":51},{"_i":"ms_004510.jpg","_t":4510,"_vc":51},{"_i":"ms_004652.jpg","_t":4652,"_vc":52},{"_i":"ms_004704.jpg","_t":4704,"_vc":64},{"_i":"ms_004890.jpg","_t":4890,"_vc":96},{"_i":"ms_004907.jpg","_t":4907,"_vc":96},{"_i":"ms_005000.jpg","_t":5000,"_vc":98},{"_i":"ms_005122.jpg","_t":5122,"_vc":98},{"_i":"ms_005216.jpg","_t":5216,"_vc":99},{"_i":"ms_005319.jpg","_t":5319,"_vc":99},{"_i":"ms_005411.jpg","_t":5411,"_vc":99},{"_i":"ms_005518.jpg","_t":5518,"_vc":100},{"_i":"ms_005604.jpg","_t":5604,"_vc":100},{"_i":"ms_005706.jpg","_t":5706,"_vc":100},{"_i":"ms_005808.jpg","_t":5808,"_vc":100},{"_i":"ms_005848.jpg","_t":5848,"_vc":100}],[{"_i":"ms_000000.jpg","_t":0,"_vc":0},{"_i":"ms_001844.jpg","_t":1844,"_vc":17},{"_i":"ms_001895.jpg","_t":1895,"_vc":18},{"_i":"ms_002003.jpg","_t":2003,"_vc":37},{"_i":"ms_002152.jpg","_t":2152,"_vc":37},{"_i":"ms_002384.jpg","_t":2384,"_vc":37},{"_i":"ms_002401.jpg","_t":2401,"_vc":37},{"_i":"ms_002418.jpg","_t":2418,"_vc":37},{"_i":"ms_002437.jpg","_t":2437,"_vc":37},{"_i":"ms_002455.jpg","_t":2455,"_vc":37},{"_i":"ms_002516.jpg","_t":2516,"_vc":37},{"_i":"ms_002615.jpg","_t":2615,"_vc":48},{"_i":"ms_002717.jpg","_t":2717,"_vc":48},{"_i":"ms_002815.jpg","_t":2815,"_vc":47},{"_i":"ms_002903.jpg","_t":2903,"_vc":47},{"_i":"ms_003015.jpg","_t":3015,"_vc":47},{"_i":"ms_003108.jpg","_t":3108,"_vc":47},{"_i":"ms_003216.jpg","_t":3216,"_vc":47},{"_i":"ms_003328.jpg","_t":3328,"_vc":47},{"_i":"ms_003416.jpg","_t":3416,"_vc":47},{"_i":"ms_003536.jpg","_t":3536,"_vc":47},{"_i":"ms_003603.jpg","_t":3603,"_vc":47},{"_i":"ms_003711.jpg","_t":3711,"_vc":47},{"_i":"ms_003827.jpg","_t":3827,"_vc":47},{"_i":"ms_003931.jpg","_t":3931,"_vc":47},{"_i":"ms_004012.jpg","_t":4012,"_vc":29},{"_i":"ms_004107.jpg","_t":4107,"_vc":53},{"_i":"ms_004216.jpg","_t":4216,"_vc":52},{"_i":"ms_004309.jpg","_t":4309,"_vc":52},{"_i":"ms_004410.jpg","_t":4410,"_vc":52},{"_i":"ms_004503.jpg","_t":4503,"_vc":52},{"_i":"ms_004625.jpg","_t":4625,"_vc":52},{"_i":"ms_004806.jpg","_t":4806,"_vc":99},{"_i":"ms_004923.jpg","_t":4923,"_vc":99},{"_i":"ms_005005.jpg","_t":5005,"_vc":99},{"_i":"ms_005127.jpg","_t":5127,"_vc":100}]],"visualComplete":[4810,5518,5127],"lighthouse":[35,35,35],"pagespeed":[63,63,63]}}