{"_ts":[1504309884],"_r":{"breakdown":{"html":{"bytes":[52683],"requests":[16]},"js":{"bytes":[208700],"requests":[14]},"css":{"bytes":[4771],"requests":[1]},"image":{"bytes":[404273],"requests":[29]},"flash":{"bytes":[0],"requests":[0]},"font":{"bytes":[191328],"requests":[7]},"other":{"bytes":[0],"requests":[3]}},"date":[1504309884],"domElements":[825],"domInteractive":[3009],"firstPaint":[2644],"fullyLoaded":[12207],"id":["170901_B4_4789e1e98c0879c68088fb72d9cb3812"],"loadTime":[6582],"render":[3417],"SpeedIndex":[3643],"TTFB":[722],"videoFrames":[[{"_i":"ms_000000.jpg","_t":0,"_vc":0},{"_i":"ms_003417.jpg","_t":3417,"_vc":20},{"_i":"ms_003483.jpg","_t":3483,"_vc":20},{"_i":"ms_003546.jpg","_t":3546,"_vc":77},{"_i":"ms_003763.jpg","_t":3763,"_vc":99},{"_i":"ms_003779.jpg","_t":3779,"_vc":99},{"_i":"ms_003799.jpg","_t":3799,"_vc":99},{"_i":"ms_003818.jpg","_t":3818,"_vc":99},{"_i":"ms_003836.jpg","_t":3836,"_vc":99},{"_i":"ms_003857.jpg","_t":3857,"_vc":99},{"_i":"ms_003922.jpg","_t":3922,"_vc":100},{"_i":"ms_004048.jpg","_t":4048,"_vc":99},{"_i":"ms_004103.jpg","_t":4103,"_vc":97},{"_i":"ms_004213.jpg","_t":4213,"_vc":96},{"_i":"ms_004300.jpg","_t":4300,"_vc":95},{"_i":"ms_004404.jpg","_t":4404,"_vc":95},{"_i":"ms_004501.jpg","_t":4501,"_vc":95},{"_i":"ms_004608.jpg","_t":4608,"_vc":96},{"_i":"ms_004700.jpg","_t":4700,"_vc":96},{"_i":"ms_004819.jpg","_t":4819,"_vc":96},{"_i":"ms_004900.jpg","_t":4900,"_vc":96},{"_i":"ms_005002.jpg","_t":5002,"_vc":96},{"_i":"ms_005121.jpg","_t":5121,"_vc":97},{"_i":"ms_005212.jpg","_t":5212,"_vc":99},{"_i":"ms_005313.jpg","_t":5313,"_vc":99},{"_i":"ms_005423.jpg","_t":5423,"_vc":100},{"_i":"ms_005513.jpg","_t":5513,"_vc":100},{"_i":"ms_005616.jpg","_t":5616,"_vc":100},{"_i":"ms_005714.jpg","_t":5714,"_vc":100},{"_i":"ms_005807.jpg","_t":5807,"_vc":100},{"_i":"ms_005900.jpg","_t":5900,"_vc":100},{"_i":"ms_006031.jpg","_t":6031,"_vc":100},{"_i":"ms_006110.jpg","_t":6110,"_vc":100},{"_i":"ms_006203.jpg","_t":6203,"_vc":100},{"_i":"ms_006322.jpg","_t":6322,"_vc":99},{"_i":"ms_006417.jpg","_t":6417,"_vc":99},{"_i":"ms_006506.jpg","_t":6506,"_vc":99},{"_i":"ms_006648.jpg","_t":6648,"_vc":99},{"_i":"ms_006708.jpg","_t":6708,"_vc":99},{"_i":"ms_006844.jpg","_t":6844,"_vc":98},{"_i":"ms_006901.jpg","_t":6901,"_vc":98},{"_i":"ms_007017.jpg","_t":7017,"_vc":99},{"_i":"ms_007133.jpg","_t":7133,"_vc":99},{"_i":"ms_007200.jpg","_t":7200,"_vc":99},{"_i":"ms_007302.jpg","_t":7302,"_vc":99},{"_i":"ms_007409.jpg","_t":7409,"_vc":97},{"_i":"ms_007608.jpg","_t":7608,"_vc":98},{"_i":"ms_007757.jpg","_t":7757,"_vc":98},{"_i":"ms_007836.jpg","_t":7836,"_vc":99},{"_i":"ms_007904.jpg","_t":7904,"_vc":100},{"_i":"ms_008060.jpg","_t":8060,"_vc":100},{"_i":"ms_008123.jpg","_t":8123,"_vc":100},{"_i":"ms_008153.jpg","_t":8153,"_vc":100}]],"visualComplete":[3922],"lighthouse":[null],"pagespeed":[59]}}