{"_ts":[1502833012,1502920188,1503007183,1503094320,1503181385,1503267894],"_r":{"breakdown":{"html":{"bytes":[37150,38127,37996,37971,38000,37920],"requests":[13,14,14,14,16,12]},"js":{"bytes":[120033,119651,119642,119799,119799,119798],"requests":[14,14,14,14,14,14]},"css":{"bytes":[4771,4771,4771,4771,4771,4771],"requests":[1,1,1,1,1,1]},"image":{"bytes":[57075,65049,74611,76548,79992,101184],"requests":[17,17,16,17,16,17]},"flash":{"bytes":[0,0,0,0,0,0],"requests":[0,0,0,0,0,0]},"font":{"bytes":[191328,191328,191328,191328,191328,191328],"requests":[7,7,7,7,7,7]},"other":{"bytes":[0,0,0,0,0,0],"requests":[3,3,2,3,2,3]}},"date":[1502833012,1502920188,1503007183,1503094320,1503181385,1503267894],"domElements":[1218,1225,1213,1212,1213,1213],"domInteractive":[3891,6870,4287,3978,4040,4133],"firstPaint":[3804,6490,3966,3631,3667,3785],"fullyLoaded":[16388,20560,16879,16705,16654,19120],"id":["170815_BB_1Y0Y","170816_XN_19df87bc83fc1698276499f1e78be1a3","170817_HV_f0d01bbc27d7bceede99aabe260411f8","170818_EX_2cfe95f004390cbc2aa8463ddaa55104","170819_87_0ed506a36e131a4ec40d893d17690c8f","170820_2N_c709168d2a7fa8dbe1bb2ee6dd40a019"],"loadTime":[6407,9679,7254,6802,7090,8206],"render":[4443,7045,4494,4233,4265,4400],"SpeedIndex":[5437,7723,5077,4951,4909,5348],"TTFB":[1492,1373,1746,1490,1413,1510],"videoFrames":[[{"_i":"ms_000000.jpg","_t":0,"_vc":0},{"_i":"ms_004443.jpg","_t":4443,"_vc":26},{"_i":"ms_004525.jpg","_t":4525,"_vc":29},{"_i":"ms_004543.jpg","_t":4543,"_vc":47},{"_i":"ms_004693.jpg","_t":4693,"_vc":56},{"_i":"ms_004711.jpg","_t":4711,"_vc":53},{"_i":"ms_004728.jpg","_t":4728,"_vc":52},{"_i":"ms_004761.jpg","_t":4761,"_vc":42},{"_i":"ms_004783.jpg","_t":4783,"_vc":37},{"_i":"ms_004811.jpg","_t":4811,"_vc":37},{"_i":"ms_004912.jpg","_t":4912,"_vc":37},{"_i":"ms_005200.jpg","_t":5200,"_vc":40},{"_i":"ms_005317.jpg","_t":5317,"_vc":53},{"_i":"ms_005588.jpg","_t":5588,"_vc":54},{"_i":"ms_005930.jpg","_t":5930,"_vc":59},{"_i":"ms_006022.jpg","_t":6022,"_vc":69},{"_i":"ms_006115.jpg","_t":6115,"_vc":73},{"_i":"ms_006200.jpg","_t":6200,"_vc":95},{"_i":"ms_007793.jpg","_t":7793,"_vc":97},{"_i":"ms_007810.jpg","_t":7810,"_vc":97},{"_i":"ms_007917.jpg","_t":7917,"_vc":98},{"_i":"ms_008029.jpg","_t":8029,"_vc":99},{"_i":"ms_008136.jpg","_t":8136,"_vc":99},{"_i":"ms_008265.jpg","_t":8265,"_vc":99},{"_i":"ms_008317.jpg","_t":8317,"_vc":99},{"_i":"ms_008402.jpg","_t":8402,"_vc":99},{"_i":"ms_008501.jpg","_t":8501,"_vc":100}],[{"_i":"ms_000000.jpg","_t":0,"_vc":0},{"_i":"ms_007045.jpg","_t":7045,"_vc":33},{"_i":"ms_007238.jpg","_t":7238,"_vc":32},{"_i":"ms_007268.jpg","_t":7268,"_vc":31},{"_i":"ms_007286.jpg","_t":7286,"_vc":78},{"_i":"ms_007386.jpg","_t":7386,"_vc":78},{"_i":"ms_007403.jpg","_t":7403,"_vc":79},{"_i":"ms_007421.jpg","_t":7421,"_vc":79},{"_i":"ms_007446.jpg","_t":7446,"_vc":79},{"_i":"ms_007472.jpg","_t":7472,"_vc":79},{"_i":"ms_007510.jpg","_t":7510,"_vc":79},{"_i":"ms_007616.jpg","_t":7616,"_vc":79},{"_i":"ms_007702.jpg","_t":7702,"_vc":80},{"_i":"ms_007810.jpg","_t":7810,"_vc":80},{"_i":"ms_007930.jpg","_t":7930,"_vc":80},{"_i":"ms_008113.jpg","_t":8113,"_vc":82},{"_i":"ms_008386.jpg","_t":8386,"_vc":82},{"_i":"ms_008522.jpg","_t":8522,"_vc":80},{"_i":"ms_008890.jpg","_t":8890,"_vc":83},{"_i":"ms_008907.jpg","_t":8907,"_vc":83},{"_i":"ms_009003.jpg","_t":9003,"_vc":88},{"_i":"ms_009114.jpg","_t":9114,"_vc":91},{"_i":"ms_009212.jpg","_t":9212,"_vc":97},{"_i":"ms_009302.jpg","_t":9302,"_vc":97},{"_i":"ms_009417.jpg","_t":9417,"_vc":97},{"_i":"ms_009515.jpg","_t":9515,"_vc":97},{"_i":"ms_009626.jpg","_t":9626,"_vc":97},{"_i":"ms_009700.jpg","_t":9700,"_vc":97},{"_i":"ms_009823.jpg","_t":9823,"_vc":97},{"_i":"ms_009903.jpg","_t":9903,"_vc":97},{"_i":"ms_010032.jpg","_t":10032,"_vc":97},{"_i":"ms_010127.jpg","_t":10127,"_vc":97},{"_i":"ms_010237.jpg","_t":10237,"_vc":97},{"_i":"ms_010305.jpg","_t":10305,"_vc":97},{"_i":"ms_010424.jpg","_t":10424,"_vc":97},{"_i":"ms_010513.jpg","_t":10513,"_vc":97},{"_i":"ms_010647.jpg","_t":10647,"_vc":97},{"_i":"ms_010717.jpg","_t":10717,"_vc":97},{"_i":"ms_010806.jpg","_t":10806,"_vc":97},{"_i":"ms_010921.jpg","_t":10921,"_vc":97},{"_i":"ms_011020.jpg","_t":11020,"_vc":97},{"_i":"ms_011121.jpg","_t":11121,"_vc":97},{"_i":"ms_011200.jpg","_t":11200,"_vc":97},{"_i":"ms_011307.jpg","_t":11307,"_vc":97},{"_i":"ms_011444.jpg","_t":11444,"_vc":97},{"_i":"ms_011508.jpg","_t":11508,"_vc":98},{"_i":"ms_011610.jpg","_t":11610,"_vc":99},{"_i":"ms_011728.jpg","_t":11728,"_vc":99},{"_i":"ms_011812.jpg","_t":11812,"_vc":99},{"_i":"ms_011920.jpg","_t":11920,"_vc":99},{"_i":"ms_012017.jpg","_t":12017,"_vc":99},{"_i":"ms_012505.jpg","_t":12505,"_vc":100},{"_i":"ms_013001.jpg","_t":13001,"_vc":99},{"_i":"ms_013511.jpg","_t":13511,"_vc":99},{"_i":"ms_014012.jpg","_t":14012,"_vc":99},{"_i":"ms_014508.jpg","_t":14508,"_vc":99},{"_i":"ms_015015.jpg","_t":15015,"_vc":99},{"_i":"ms_015519.jpg","_t":15519,"_vc":99},{"_i":"ms_016006.jpg","_t":16006,"_vc":99},{"_i":"ms_016510.jpg","_t":16510,"_vc":99},{"_i":"ms_017003.jpg","_t":17003,"_vc":99},{"_i":"ms_018005.jpg","_t":18005,"_vc":99},{"_i":"ms_019012.jpg","_t":19012,"_vc":99},{"_i":"ms_020012.jpg","_t":20012,"_vc":100},{"_i":"ms_021010.jpg","_t":21010,"_vc":100},{"_i":"ms_022004.jpg","_t":22004,"_vc":99},{"_i":"ms_022700.jpg","_t":22700,"_vc":100}],[{"_i":"ms_000000.jpg","_t":0,"_vc":0},{"_i":"ms_004494.jpg","_t":4494,"_vc":36},{"_i":"ms_004697.jpg","_t":4697,"_vc":37},{"_i":"ms_004717.jpg","_t":4717,"_vc":36},{"_i":"ms_004733.jpg","_t":4733,"_vc":36},{"_i":"ms_004775.jpg","_t":4775,"_vc":36},{"_i":"ms_004843.jpg","_t":4843,"_vc":30},{"_i":"ms_004878.jpg","_t":4878,"_vc":73},{"_i":"ms_004906.jpg","_t":4906,"_vc":86},{"_i":"ms_004929.jpg","_t":4929,"_vc":87},{"_i":"ms_005008.jpg","_t":5008,"_vc":89},{"_i":"ms_005100.jpg","_t":5100,"_vc":89},{"_i":"ms_005216.jpg","_t":5216,"_vc":89},{"_i":"ms_005324.jpg","_t":5324,"_vc":88},{"_i":"ms_005408.jpg","_t":5408,"_vc":90},{"_i":"ms_005507.jpg","_t":5507,"_vc":90},{"_i":"ms_005610.jpg","_t":5610,"_vc":90},{"_i":"ms_005741.jpg","_t":5741,"_vc":86},{"_i":"ms_006120.jpg","_t":6120,"_vc":87},{"_i":"ms_006272.jpg","_t":6272,"_vc":92},{"_i":"ms_006555.jpg","_t":6555,"_vc":92},{"_i":"ms_006605.jpg","_t":6605,"_vc":93},{"_i":"ms_006715.jpg","_t":6715,"_vc":94},{"_i":"ms_006814.jpg","_t":6814,"_vc":96},{"_i":"ms_006915.jpg","_t":6915,"_vc":97},{"_i":"ms_007017.jpg","_t":7017,"_vc":97},{"_i":"ms_007110.jpg","_t":7110,"_vc":97},{"_i":"ms_007210.jpg","_t":7210,"_vc":97},{"_i":"ms_007309.jpg","_t":7309,"_vc":97},{"_i":"ms_007401.jpg","_t":7401,"_vc":97},{"_i":"ms_007530.jpg","_t":7530,"_vc":97},{"_i":"ms_007608.jpg","_t":7608,"_vc":97},{"_i":"ms_007722.jpg","_t":7722,"_vc":97},{"_i":"ms_007820.jpg","_t":7820,"_vc":97},{"_i":"ms_007917.jpg","_t":7917,"_vc":97},{"_i":"ms_008015.jpg","_t":8015,"_vc":97},{"_i":"ms_008115.jpg","_t":8115,"_vc":97},{"_i":"ms_008212.jpg","_t":8212,"_vc":97},{"_i":"ms_008314.jpg","_t":8314,"_vc":97},{"_i":"ms_008416.jpg","_t":8416,"_vc":97},{"_i":"ms_008515.jpg","_t":8515,"_vc":97},{"_i":"ms_008647.jpg","_t":8647,"_vc":97},{"_i":"ms_008712.jpg","_t":8712,"_vc":97},{"_i":"ms_008811.jpg","_t":8811,"_vc":97},{"_i":"ms_008901.jpg","_t":8901,"_vc":97},{"_i":"ms_009029.jpg","_t":9029,"_vc":98},{"_i":"ms_009110.jpg","_t":9110,"_vc":99},{"_i":"ms_009227.jpg","_t":9227,"_vc":99},{"_i":"ms_009326.jpg","_t":9326,"_vc":99},{"_i":"ms_009409.jpg","_t":9409,"_vc":99},{"_i":"ms_009509.jpg","_t":9509,"_vc":99},{"_i":"ms_010007.jpg","_t":10007,"_vc":100},{"_i":"ms_010522.jpg","_t":10522,"_vc":99},{"_i":"ms_011016.jpg","_t":11016,"_vc":99},{"_i":"ms_011519.jpg","_t":11519,"_vc":100},{"_i":"ms_012007.jpg","_t":12007,"_vc":99},{"_i":"ms_012507.jpg","_t":12507,"_vc":99},{"_i":"ms_013005.jpg","_t":13005,"_vc":100},{"_i":"ms_013521.jpg","_t":13521,"_vc":99},{"_i":"ms_014011.jpg","_t":14011,"_vc":100},{"_i":"ms_015008.jpg","_t":15008,"_vc":99},{"_i":"ms_016000.jpg","_t":16000,"_vc":100},{"_i":"ms_017001.jpg","_t":17001,"_vc":99},{"_i":"ms_018039.jpg","_t":18039,"_vc":100},{"_i":"ms_019011.jpg","_t":19011,"_vc":99},{"_i":"ms_019061.jpg","_t":19061,"_vc":100}],[{"_i":"ms_000000.jpg","_t":0,"_vc":0},{"_i":"ms_004233.jpg","_t":4233,"_vc":25},{"_i":"ms_004384.jpg","_t":4384,"_vc":25},{"_i":"ms_004413.jpg","_t":4413,"_vc":71},{"_i":"ms_004548.jpg","_t":4548,"_vc":76},{"_i":"ms_004565.jpg","_t":4565,"_vc":76},{"_i":"ms_004584.jpg","_t":4584,"_vc":76},{"_i":"ms_004616.jpg","_t":4616,"_vc":77},{"_i":"ms_004650.jpg","_t":4650,"_vc":77},{"_i":"ms_004678.jpg","_t":4678,"_vc":77},{"_i":"ms_004702.jpg","_t":4702,"_vc":77},{"_i":"ms_004814.jpg","_t":4814,"_vc":77},{"_i":"ms_004918.jpg","_t":4918,"_vc":77},{"_i":"ms_005072.jpg","_t":5072,"_vc":77},{"_i":"ms_005124.jpg","_t":5124,"_vc":77},{"_i":"ms_005461.jpg","_t":5461,"_vc":78},{"_i":"ms_005614.jpg","_t":5614,"_vc":74},{"_i":"ms_005822.jpg","_t":5822,"_vc":79},{"_i":"ms_006037.jpg","_t":6037,"_vc":80},{"_i":"ms_006105.jpg","_t":6105,"_vc":82},{"_i":"ms_006225.jpg","_t":6225,"_vc":90},{"_i":"ms_006319.jpg","_t":6319,"_vc":97},{"_i":"ms_006405.jpg","_t":6405,"_vc":97},{"_i":"ms_006524.jpg","_t":6524,"_vc":97},{"_i":"ms_006614.jpg","_t":6614,"_vc":97},{"_i":"ms_006720.jpg","_t":6720,"_vc":97},{"_i":"ms_006804.jpg","_t":6804,"_vc":97},{"_i":"ms_006939.jpg","_t":6939,"_vc":97},{"_i":"ms_007016.jpg","_t":7016,"_vc":97},{"_i":"ms_007124.jpg","_t":7124,"_vc":97},{"_i":"ms_007200.jpg","_t":7200,"_vc":97},{"_i":"ms_007316.jpg","_t":7316,"_vc":97},{"_i":"ms_007407.jpg","_t":7407,"_vc":97},{"_i":"ms_007520.jpg","_t":7520,"_vc":97},{"_i":"ms_007615.jpg","_t":7615,"_vc":97},{"_i":"ms_007716.jpg","_t":7716,"_vc":97},{"_i":"ms_007800.jpg","_t":7800,"_vc":97},{"_i":"ms_007903.jpg","_t":7903,"_vc":97},{"_i":"ms_008019.jpg","_t":8019,"_vc":97},{"_i":"ms_008138.jpg","_t":8138,"_vc":97},{"_i":"ms_008240.jpg","_t":8240,"_vc":97},{"_i":"ms_008324.jpg","_t":8324,"_vc":97},{"_i":"ms_008409.jpg","_t":8409,"_vc":98},{"_i":"ms_008513.jpg","_t":8513,"_vc":99},{"_i":"ms_008646.jpg","_t":8646,"_vc":99},{"_i":"ms_008715.jpg","_t":8715,"_vc":99},{"_i":"ms_008805.jpg","_t":8805,"_vc":99},{"_i":"ms_008900.jpg","_t":8900,"_vc":99},{"_i":"ms_009035.jpg","_t":9035,"_vc":99},{"_i":"ms_009103.jpg","_t":9103,"_vc":99},{"_i":"ms_009211.jpg","_t":9211,"_vc":100},{"_i":"ms_009504.jpg","_t":9504,"_vc":99},{"_i":"ms_010034.jpg","_t":10034,"_vc":99},{"_i":"ms_010526.jpg","_t":10526,"_vc":100},{"_i":"ms_011003.jpg","_t":11003,"_vc":100},{"_i":"ms_011514.jpg","_t":11514,"_vc":99},{"_i":"ms_012013.jpg","_t":12013,"_vc":99},{"_i":"ms_012504.jpg","_t":12504,"_vc":99},{"_i":"ms_013018.jpg","_t":13018,"_vc":99},{"_i":"ms_013536.jpg","_t":13536,"_vc":99},{"_i":"ms_014018.jpg","_t":14018,"_vc":99},{"_i":"ms_015000.jpg","_t":15000,"_vc":99},{"_i":"ms_016007.jpg","_t":16007,"_vc":99},{"_i":"ms_017018.jpg","_t":17018,"_vc":99},{"_i":"ms_018005.jpg","_t":18005,"_vc":99},{"_i":"ms_018914.jpg","_t":18914,"_vc":100}],[{"_i":"ms_000000.jpg","_t":0,"_vc":0},{"_i":"ms_004265.jpg","_t":4265,"_vc":27},{"_i":"ms_004483.jpg","_t":4483,"_vc":26},{"_i":"ms_004521.jpg","_t":4521,"_vc":78},{"_i":"ms_004545.jpg","_t":4545,"_vc":78},{"_i":"ms_004562.jpg","_t":4562,"_vc":78},{"_i":"ms_004581.jpg","_t":4581,"_vc":78},{"_i":"ms_004632.jpg","_t":4632,"_vc":78},{"_i":"ms_004649.jpg","_t":4649,"_vc":78},{"_i":"ms_004667.jpg","_t":4667,"_vc":79},{"_i":"ms_004714.jpg","_t":4714,"_vc":80},{"_i":"ms_004800.jpg","_t":4800,"_vc":81},{"_i":"ms_004905.jpg","_t":4905,"_vc":81},{"_i":"ms_005015.jpg","_t":5015,"_vc":81},{"_i":"ms_005136.jpg","_t":5136,"_vc":81},{"_i":"ms_005573.jpg","_t":5573,"_vc":83},{"_i":"ms_005823.jpg","_t":5823,"_vc":81},{"_i":"ms_006197.jpg","_t":6197,"_vc":84},{"_i":"ms_006215.jpg","_t":6215,"_vc":84},{"_i":"ms_006313.jpg","_t":6313,"_vc":89},{"_i":"ms_006408.jpg","_t":6408,"_vc":92},{"_i":"ms_006517.jpg","_t":6517,"_vc":97},{"_i":"ms_006605.jpg","_t":6605,"_vc":97},{"_i":"ms_006705.jpg","_t":6705,"_vc":97},{"_i":"ms_006800.jpg","_t":6800,"_vc":97},{"_i":"ms_006917.jpg","_t":6917,"_vc":97},{"_i":"ms_007012.jpg","_t":7012,"_vc":97},{"_i":"ms_007102.jpg","_t":7102,"_vc":97},{"_i":"ms_007205.jpg","_t":7205,"_vc":97},{"_i":"ms_007342.jpg","_t":7342,"_vc":97},{"_i":"ms_007415.jpg","_t":7415,"_vc":97},{"_i":"ms_007510.jpg","_t":7510,"_vc":97},{"_i":"ms_007613.jpg","_t":7613,"_vc":97},{"_i":"ms_007701.jpg","_t":7701,"_vc":97},{"_i":"ms_007818.jpg","_t":7818,"_vc":97},{"_i":"ms_007917.jpg","_t":7917,"_vc":97},{"_i":"ms_008007.jpg","_t":8007,"_vc":97},{"_i":"ms_008103.jpg","_t":8103,"_vc":97},{"_i":"ms_008203.jpg","_t":8203,"_vc":97},{"_i":"ms_008308.jpg","_t":8308,"_vc":97},{"_i":"ms_008404.jpg","_t":8404,"_vc":97},{"_i":"ms_008511.jpg","_t":8511,"_vc":97},{"_i":"ms_008608.jpg","_t":8608,"_vc":97},{"_i":"ms_008726.jpg","_t":8726,"_vc":98},{"_i":"ms_008810.jpg","_t":8810,"_vc":98},{"_i":"ms_008903.jpg","_t":8903,"_vc":99},{"_i":"ms_009029.jpg","_t":9029,"_vc":99},{"_i":"ms_009101.jpg","_t":9101,"_vc":99},{"_i":"ms_009213.jpg","_t":9213,"_vc":99},{"_i":"ms_009502.jpg","_t":9502,"_vc":100},{"_i":"ms_010000.jpg","_t":10000,"_vc":100},{"_i":"ms_010503.jpg","_t":10503,"_vc":99},{"_i":"ms_011033.jpg","_t":11033,"_vc":100},{"_i":"ms_011507.jpg","_t":11507,"_vc":100},{"_i":"ms_012047.jpg","_t":12047,"_vc":100},{"_i":"ms_012514.jpg","_t":12514,"_vc":99},{"_i":"ms_013002.jpg","_t":13002,"_vc":99},{"_i":"ms_013533.jpg","_t":13533,"_vc":100},{"_i":"ms_014006.jpg","_t":14006,"_vc":100},{"_i":"ms_015001.jpg","_t":15001,"_vc":100},{"_i":"ms_016008.jpg","_t":16008,"_vc":100},{"_i":"ms_017009.jpg","_t":17009,"_vc":100},{"_i":"ms_018003.jpg","_t":18003,"_vc":99},{"_i":"ms_018858.jpg","_t":18858,"_vc":100}],[{"_i":"ms_000000.jpg","_t":0,"_vc":0},{"_i":"ms_004400.jpg","_t":4400,"_vc":28},{"_i":"ms_004639.jpg","_t":4639,"_vc":27},{"_i":"ms_004668.jpg","_t":4668,"_vc":56},{"_i":"ms_004686.jpg","_t":4686,"_vc":80},{"_i":"ms_004704.jpg","_t":4704,"_vc":80},{"_i":"ms_004741.jpg","_t":4741,"_vc":80},{"_i":"ms_004770.jpg","_t":4770,"_vc":80},{"_i":"ms_004811.jpg","_t":4811,"_vc":80},{"_i":"ms_004840.jpg","_t":4840,"_vc":81},{"_i":"ms_004916.jpg","_t":4916,"_vc":82},{"_i":"ms_005010.jpg","_t":5010,"_vc":82},{"_i":"ms_005144.jpg","_t":5144,"_vc":83},{"_i":"ms_005246.jpg","_t":5246,"_vc":83},{"_i":"ms_005481.jpg","_t":5481,"_vc":84},{"_i":"ms_005549.jpg","_t":5549,"_vc":84},{"_i":"ms_005750.jpg","_t":5750,"_vc":84},{"_i":"ms_005955.jpg","_t":5955,"_vc":83},{"_i":"ms_006129.jpg","_t":6129,"_vc":83},{"_i":"ms_006215.jpg","_t":6215,"_vc":85},{"_i":"ms_006305.jpg","_t":6305,"_vc":85},{"_i":"ms_006408.jpg","_t":6408,"_vc":86},{"_i":"ms_006512.jpg","_t":6512,"_vc":86},{"_i":"ms_006614.jpg","_t":6614,"_vc":86},{"_i":"ms_006709.jpg","_t":6709,"_vc":86},{"_i":"ms_006821.jpg","_t":6821,"_vc":85},{"_i":"ms_006914.jpg","_t":6914,"_vc":85},{"_i":"ms_007014.jpg","_t":7014,"_vc":83},{"_i":"ms_007112.jpg","_t":7112,"_vc":83},{"_i":"ms_007203.jpg","_t":7203,"_vc":83},{"_i":"ms_007304.jpg","_t":7304,"_vc":84},{"_i":"ms_007402.jpg","_t":7402,"_vc":85},{"_i":"ms_007523.jpg","_t":7523,"_vc":85},{"_i":"ms_007621.jpg","_t":7621,"_vc":85},{"_i":"ms_007716.jpg","_t":7716,"_vc":86},{"_i":"ms_007822.jpg","_t":7822,"_vc":86},{"_i":"ms_007907.jpg","_t":7907,"_vc":86},{"_i":"ms_008011.jpg","_t":8011,"_vc":86},{"_i":"ms_008119.jpg","_t":8119,"_vc":85},{"_i":"ms_008243.jpg","_t":8243,"_vc":85},{"_i":"ms_008320.jpg","_t":8320,"_vc":83},{"_i":"ms_008407.jpg","_t":8407,"_vc":89},{"_i":"ms_008529.jpg","_t":8529,"_vc":91},{"_i":"ms_008606.jpg","_t":8606,"_vc":97},{"_i":"ms_008701.jpg","_t":8701,"_vc":97},{"_i":"ms_008802.jpg","_t":8802,"_vc":97},{"_i":"ms_008915.jpg","_t":8915,"_vc":98},{"_i":"ms_009000.jpg","_t":9000,"_vc":99},{"_i":"ms_009101.jpg","_t":9101,"_vc":99},{"_i":"ms_009205.jpg","_t":9205,"_vc":99},{"_i":"ms_009304.jpg","_t":9304,"_vc":99},{"_i":"ms_009506.jpg","_t":9506,"_vc":99},{"_i":"ms_010032.jpg","_t":10032,"_vc":99},{"_i":"ms_010516.jpg","_t":10516,"_vc":99},{"_i":"ms_011005.jpg","_t":11005,"_vc":99},{"_i":"ms_011503.jpg","_t":11503,"_vc":99},{"_i":"ms_012014.jpg","_t":12014,"_vc":99},{"_i":"ms_012543.jpg","_t":12543,"_vc":99},{"_i":"ms_013026.jpg","_t":13026,"_vc":99},{"_i":"ms_013512.jpg","_t":13512,"_vc":99},{"_i":"ms_014004.jpg","_t":14004,"_vc":99},{"_i":"ms_015019.jpg","_t":15019,"_vc":99},{"_i":"ms_016003.jpg","_t":16003,"_vc":99},{"_i":"ms_017035.jpg","_t":17035,"_vc":99},{"_i":"ms_018014.jpg","_t":18014,"_vc":99},{"_i":"ms_019007.jpg","_t":19007,"_vc":99},{"_i":"ms_020003.jpg","_t":20003,"_vc":99},{"_i":"ms_021004.jpg","_t":21004,"_vc":99},{"_i":"ms_021298.jpg","_t":21298,"_vc":100}]],"visualComplete":[8501,12505,10007,9211,9502,21298],"lighthouse":[null,36,null,36,null,null],"pagespeed":[73,63,63,63,63,63]}}