{"_ts":[1535810631],"_r":{"breakdown":{"html":{"bytes":[26473],"requests":[14]},"js":{"bytes":[286661],"requests":[17]},"css":{"bytes":[19386],"requests":[3]},"image":{"bytes":[485073],"requests":[21]},"flash":{"bytes":[0],"requests":[0]},"font":{"bytes":[113946],"requests":[6]},"video":{"bytes":[0],"requests":[0]},"other":{"bytes":[1005],"requests":[4]}},"date":[1535810631],"domElements":[868],"domInteractive":[1671],"firstPaint":[1370.8000000042],"fullyLoaded":[5674],"id":["180901_86_37034800b61c879d8e22a8ef25ca875c"],"loadTime":[5475],"render":[1730],"SpeedIndex":[3564],"TTFB":[522],"videoFrames":[[{"_i":"ms_000000.jpg","_t":0,"_vc":0},{"_i":"ms_001730.jpg","_t":1730,"_vc":21},{"_i":"ms_001931.jpg","_t":1931,"_vc":18},{"_i":"ms_001987.jpg","_t":1987,"_vc":18},{"_i":"ms_002163.jpg","_t":2163,"_vc":22},{"_i":"ms_002725.jpg","_t":2725,"_vc":25},{"_i":"ms_002753.jpg","_t":2753,"_vc":25},{"_i":"ms_002994.jpg","_t":2994,"_vc":31},{"_i":"ms_003019.jpg","_t":3019,"_vc":31},{"_i":"ms_003036.jpg","_t":3036,"_vc":31},{"_i":"ms_003077.jpg","_t":3077,"_vc":31},{"_i":"ms_003191.jpg","_t":3191,"_vc":31},{"_i":"ms_003247.jpg","_t":3247,"_vc":31},{"_i":"ms_003263.jpg","_t":3263,"_vc":31},{"_i":"ms_003294.jpg","_t":3294,"_vc":31},{"_i":"ms_003314.jpg","_t":3314,"_vc":31},{"_i":"ms_003343.jpg","_t":3343,"_vc":31},{"_i":"ms_003428.jpg","_t":3428,"_vc":31},{"_i":"ms_003490.jpg","_t":3490,"_vc":31},{"_i":"ms_003698.jpg","_t":3698,"_vc":31},{"_i":"ms_003715.jpg","_t":3715,"_vc":34},{"_i":"ms_003737.jpg","_t":3737,"_vc":28},{"_i":"ms_003754.jpg","_t":3754,"_vc":26},{"_i":"ms_003778.jpg","_t":3778,"_vc":33},{"_i":"ms_003799.jpg","_t":3799,"_vc":27},{"_i":"ms_003825.jpg","_t":3825,"_vc":25},{"_i":"ms_003843.jpg","_t":3843,"_vc":34},{"_i":"ms_003861.jpg","_t":3861,"_vc":41},{"_i":"ms_003884.jpg","_t":3884,"_vc":51},{"_i":"ms_003908.jpg","_t":3908,"_vc":46},{"_i":"ms_003927.jpg","_t":3927,"_vc":50},{"_i":"ms_003946.jpg","_t":3946,"_vc":50},{"_i":"ms_004034.jpg","_t":4034,"_vc":50},{"_i":"ms_004321.jpg","_t":4321,"_vc":99},{"_i":"ms_005366.jpg","_t":5366,"_vc":99},{"_i":"ms_005475.jpg","_t":5475,"_vc":100},{"_i":"ms_005586.jpg","_t":5586,"_vc":99},{"_i":"ms_005674.jpg","_t":5674,"_vc":100}]],"visualComplete":[5475],"lighthouse":[35],"pagespeed":[42]}}