{"_ts":[1564794960,1564882258,1564969604,1565057821,1565145336,1565232405],"_r":{"breakdown":{"html":{"bytes":[0,0,0,0,0,0],"requests":[0,0,0,0,0,0]},"js":{"bytes":[0,0,0,0,0,0],"requests":[0,0,0,0,0,0]},"css":{"bytes":[0,0,0,0,0,0],"requests":[0,0,0,0,0,0]},"image":{"bytes":[0,0,0,0,0,0],"requests":[0,0,0,0,0,0]},"flash":{"bytes":[0,0,0,0,0,0],"requests":[0,0,0,0,0,0]},"font":{"bytes":[0,0,0,0,0,0],"requests":[0,0,0,0,0,0]},"video":{"bytes":[0,0,0,0,0,0],"requests":[0,0,0,0,0,0]},"other":{"bytes":[0,0,0,0,0,0],"requests":[0,0,0,0,0,0]}},"date":[1564794960,1564882258,1564969604,1565057821,1565145336,1565232405],"domElements":[null,null,null,null,null,null],"domInteractive":[0,0,0,0,0,0],"firstPaint":[0,0,0,0,0,0],"fullyLoaded":[0,0,0,0,0,0],"id":["190803_JF_b69993eebf8411f606a62bef826353da","190804_BV_0052ee9fecbc1e97b80b214d2019851d","190805_JV_eb092289f2ddcd5b887dc963bd901f71","190806_GY_6154cc53254d1b6694bd9a45f0f60ace","190807_17_b2fbda6425853ff06bc6d2c0f2ab826e","190808_73_171ae527a6f87e4c056fcc24a6fc4167"],"loadTime":[0,0,0,0,0,0],"render":[0,0,0,0,0,0],"SpeedIndex":[0,0,0,0,0,0],"TTFB":[0,0,0,0,0,0],"videoFrames":[[{"_i":"ms_000000.jpg","_t":0,"_vc":100}],[{"_i":"ms_000000.jpg","_t":0,"_vc":100}],[{"_i":"ms_000000.jpg","_t":0,"_vc":100}],[{"_i":"ms_000000.jpg","_t":0,"_vc":100}],[{"_i":"ms_000000.jpg","_t":0,"_vc":100}],[{"_i":"ms_000000.jpg","_t":0,"_vc":100}]],"visualComplete":[0,0,0,0,0,0],"lighthouse":[null,null,null,null,null,null],"pagespeed":[68,68,68,68,68,68]}}