{"_ts":[1509577169,1509664577,1509751157],"_r":{"breakdown":{"html":{"bytes":[46126,46076,46126],"requests":[15,13,15]},"js":{"bytes":[285954,285956,286062],"requests":[16,16,16]},"css":{"bytes":[4833,4833,4833],"requests":[1,1,1]},"image":{"bytes":[151210,151780,151213],"requests":[20,21,20]},"flash":{"bytes":[0,0,0],"requests":[0,0,0]},"font":{"bytes":[111057,111057,111057],"requests":[6,6,6]},"video":{"bytes":[0,0,0],"requests":[0,0,0]},"other":{"bytes":[430,430,430],"requests":[4,5,4]}},"date":[1509577169,1509664577,1509751157],"domElements":[897,897,897],"domInteractive":[3009,2510,2990],"firstPaint":[2102,2078,2065],"fullyLoaded":[11870,13092,13313],"id":["171101_ZW_5a20930c8db9bb3124b18580a51d5d85","171102_YN_09dec77d16fb818d9c4c53ebc75d1088","171103_GS_7263555ef737a6e232df23d292bd35e0"],"loadTime":[6358,7567,7020],"render":[2637,2648,2584],"SpeedIndex":[3407,3156,3362],"TTFB":[1158,1177,1149],"videoFrames":[[{"_i":"ms_000000.jpg","_t":0,"_vc":0},{"_i":"ms_002637.jpg","_t":2637,"_vc":20},{"_i":"ms_002700.jpg","_t":2700,"_vc":19},{"_i":"ms_002852.jpg","_t":2852,"_vc":16},{"_i":"ms_002902.jpg","_t":2902,"_vc":36},{"_i":"ms_003407.jpg","_t":3407,"_vc":86},{"_i":"ms_003438.jpg","_t":3438,"_vc":86},{"_i":"ms_003458.jpg","_t":3458,"_vc":85},{"_i":"ms_003474.jpg","_t":3474,"_vc":85},{"_i":"ms_003492.jpg","_t":3492,"_vc":84},{"_i":"ms_003511.jpg","_t":3511,"_vc":84},{"_i":"ms_003617.jpg","_t":3617,"_vc":82},{"_i":"ms_003709.jpg","_t":3709,"_vc":81},{"_i":"ms_003816.jpg","_t":3816,"_vc":81},{"_i":"ms_003913.jpg","_t":3913,"_vc":80},{"_i":"ms_004014.jpg","_t":4014,"_vc":87},{"_i":"ms_004106.jpg","_t":4106,"_vc":87},{"_i":"ms_004213.jpg","_t":4213,"_vc":88},{"_i":"ms_004307.jpg","_t":4307,"_vc":90},{"_i":"ms_004403.jpg","_t":4403,"_vc":91},{"_i":"ms_004512.jpg","_t":4512,"_vc":93},{"_i":"ms_004605.jpg","_t":4605,"_vc":94},{"_i":"ms_004709.jpg","_t":4709,"_vc":95},{"_i":"ms_004804.jpg","_t":4804,"_vc":96},{"_i":"ms_004911.jpg","_t":4911,"_vc":97},{"_i":"ms_005000.jpg","_t":5000,"_vc":98},{"_i":"ms_005109.jpg","_t":5109,"_vc":98},{"_i":"ms_005220.jpg","_t":5220,"_vc":99},{"_i":"ms_005306.jpg","_t":5306,"_vc":99},{"_i":"ms_005413.jpg","_t":5413,"_vc":99},{"_i":"ms_005516.jpg","_t":5516,"_vc":99},{"_i":"ms_005616.jpg","_t":5616,"_vc":99},{"_i":"ms_005701.jpg","_t":5701,"_vc":100},{"_i":"ms_005803.jpg","_t":5803,"_vc":100},{"_i":"ms_005906.jpg","_t":5906,"_vc":100},{"_i":"ms_006006.jpg","_t":6006,"_vc":100},{"_i":"ms_006121.jpg","_t":6121,"_vc":99},{"_i":"ms_006205.jpg","_t":6205,"_vc":100},{"_i":"ms_006325.jpg","_t":6325,"_vc":100},{"_i":"ms_006423.jpg","_t":6423,"_vc":100},{"_i":"ms_006515.jpg","_t":6515,"_vc":100},{"_i":"ms_006626.jpg","_t":6626,"_vc":100},{"_i":"ms_006713.jpg","_t":6713,"_vc":100},{"_i":"ms_006812.jpg","_t":6812,"_vc":99},{"_i":"ms_006902.jpg","_t":6902,"_vc":100},{"_i":"ms_007015.jpg","_t":7015,"_vc":100},{"_i":"ms_007104.jpg","_t":7104,"_vc":100},{"_i":"ms_007216.jpg","_t":7216,"_vc":100},{"_i":"ms_007302.jpg","_t":7302,"_vc":100},{"_i":"ms_007401.jpg","_t":7401,"_vc":100},{"_i":"ms_007514.jpg","_t":7514,"_vc":99},{"_i":"ms_007612.jpg","_t":7612,"_vc":99},{"_i":"ms_008025.jpg","_t":8025,"_vc":100},{"_i":"ms_008505.jpg","_t":8505,"_vc":100},{"_i":"ms_009019.jpg","_t":9019,"_vc":100},{"_i":"ms_009543.jpg","_t":9543,"_vc":100},{"_i":"ms_010065.jpg","_t":10065,"_vc":100},{"_i":"ms_010511.jpg","_t":10511,"_vc":99},{"_i":"ms_011032.jpg","_t":11032,"_vc":100},{"_i":"ms_011504.jpg","_t":11504,"_vc":100},{"_i":"ms_012014.jpg","_t":12014,"_vc":100},{"_i":"ms_012516.jpg","_t":12516,"_vc":99},{"_i":"ms_013018.jpg","_t":13018,"_vc":99},{"_i":"ms_014017.jpg","_t":14017,"_vc":99},{"_i":"ms_014738.jpg","_t":14738,"_vc":100}],[{"_i":"ms_000000.jpg","_t":0,"_vc":0},{"_i":"ms_002648.jpg","_t":2648,"_vc":20},{"_i":"ms_002708.jpg","_t":2708,"_vc":19},{"_i":"ms_002840.jpg","_t":2840,"_vc":16},{"_i":"ms_002907.jpg","_t":2907,"_vc":94},{"_i":"ms_003040.jpg","_t":3040,"_vc":94},{"_i":"ms_003057.jpg","_t":3057,"_vc":94},{"_i":"ms_003076.jpg","_t":3076,"_vc":94},{"_i":"ms_003093.jpg","_t":3093,"_vc":94},{"_i":"ms_003111.jpg","_t":3111,"_vc":94},{"_i":"ms_003206.jpg","_t":3206,"_vc":93},{"_i":"ms_003314.jpg","_t":3314,"_vc":89},{"_i":"ms_003411.jpg","_t":3411,"_vc":86},{"_i":"ms_003512.jpg","_t":3512,"_vc":84},{"_i":"ms_003601.jpg","_t":3601,"_vc":83},{"_i":"ms_003709.jpg","_t":3709,"_vc":82},{"_i":"ms_003801.jpg","_t":3801,"_vc":82},{"_i":"ms_003920.jpg","_t":3920,"_vc":85},{"_i":"ms_004017.jpg","_t":4017,"_vc":85},{"_i":"ms_004108.jpg","_t":4108,"_vc":86},{"_i":"ms_004217.jpg","_t":4217,"_vc":87},{"_i":"ms_004305.jpg","_t":4305,"_vc":89},{"_i":"ms_004417.jpg","_t":4417,"_vc":91},{"_i":"ms_004520.jpg","_t":4520,"_vc":92},{"_i":"ms_004618.jpg","_t":4618,"_vc":94},{"_i":"ms_004710.jpg","_t":4710,"_vc":95},{"_i":"ms_004800.jpg","_t":4800,"_vc":96},{"_i":"ms_004919.jpg","_t":4919,"_vc":97},{"_i":"ms_005001.jpg","_t":5001,"_vc":98},{"_i":"ms_005128.jpg","_t":5128,"_vc":99},{"_i":"ms_005202.jpg","_t":5202,"_vc":99},{"_i":"ms_005309.jpg","_t":5309,"_vc":99},{"_i":"ms_005412.jpg","_t":5412,"_vc":99},{"_i":"ms_005516.jpg","_t":5516,"_vc":99},{"_i":"ms_005616.jpg","_t":5616,"_vc":99},{"_i":"ms_005716.jpg","_t":5716,"_vc":100},{"_i":"ms_005814.jpg","_t":5814,"_vc":99},{"_i":"ms_005917.jpg","_t":5917,"_vc":99},{"_i":"ms_006015.jpg","_t":6015,"_vc":99},{"_i":"ms_006179.jpg","_t":6179,"_vc":99},{"_i":"ms_006217.jpg","_t":6217,"_vc":99},{"_i":"ms_006319.jpg","_t":6319,"_vc":99},{"_i":"ms_006419.jpg","_t":6419,"_vc":99},{"_i":"ms_006516.jpg","_t":6516,"_vc":99},{"_i":"ms_006612.jpg","_t":6612,"_vc":99},{"_i":"ms_006713.jpg","_t":6713,"_vc":99},{"_i":"ms_006813.jpg","_t":6813,"_vc":99},{"_i":"ms_006908.jpg","_t":6908,"_vc":100},{"_i":"ms_007028.jpg","_t":7028,"_vc":99},{"_i":"ms_007101.jpg","_t":7101,"_vc":99},{"_i":"ms_007202.jpg","_t":7202,"_vc":99},{"_i":"ms_007328.jpg","_t":7328,"_vc":100},{"_i":"ms_007411.jpg","_t":7411,"_vc":99},{"_i":"ms_007500.jpg","_t":7500,"_vc":99},{"_i":"ms_007601.jpg","_t":7601,"_vc":99},{"_i":"ms_008023.jpg","_t":8023,"_vc":99},{"_i":"ms_008520.jpg","_t":8520,"_vc":99},{"_i":"ms_009054.jpg","_t":9054,"_vc":99},{"_i":"ms_009508.jpg","_t":9508,"_vc":99},{"_i":"ms_010000.jpg","_t":10000,"_vc":99},{"_i":"ms_010511.jpg","_t":10511,"_vc":100},{"_i":"ms_011003.jpg","_t":11003,"_vc":99},{"_i":"ms_011507.jpg","_t":11507,"_vc":99},{"_i":"ms_012055.jpg","_t":12055,"_vc":99},{"_i":"ms_012520.jpg","_t":12520,"_vc":100},{"_i":"ms_013023.jpg","_t":13023,"_vc":100},{"_i":"ms_014000.jpg","_t":14000,"_vc":100},{"_i":"ms_015012.jpg","_t":15012,"_vc":99},{"_i":"ms_015651.jpg","_t":15651,"_vc":100}],[{"_i":"ms_000000.jpg","_t":0,"_vc":0},{"_i":"ms_002584.jpg","_t":2584,"_vc":20},{"_i":"ms_002642.jpg","_t":2642,"_vc":19},{"_i":"ms_002776.jpg","_t":2776,"_vc":16},{"_i":"ms_002828.jpg","_t":2828,"_vc":36},{"_i":"ms_003420.jpg","_t":3420,"_vc":85},{"_i":"ms_003447.jpg","_t":3447,"_vc":85},{"_i":"ms_003465.jpg","_t":3465,"_vc":84},{"_i":"ms_003482.jpg","_t":3482,"_vc":84},{"_i":"ms_003499.jpg","_t":3499,"_vc":84},{"_i":"ms_003517.jpg","_t":3517,"_vc":84},{"_i":"ms_003609.jpg","_t":3609,"_vc":82},{"_i":"ms_003705.jpg","_t":3705,"_vc":82},{"_i":"ms_003806.jpg","_t":3806,"_vc":87},{"_i":"ms_003913.jpg","_t":3913,"_vc":87},{"_i":"ms_004004.jpg","_t":4004,"_vc":87},{"_i":"ms_004110.jpg","_t":4110,"_vc":88},{"_i":"ms_004207.jpg","_t":4207,"_vc":89},{"_i":"ms_004304.jpg","_t":4304,"_vc":91},{"_i":"ms_004410.jpg","_t":4410,"_vc":91},{"_i":"ms_004503.jpg","_t":4503,"_vc":92},{"_i":"ms_004613.jpg","_t":4613,"_vc":94},{"_i":"ms_004706.jpg","_t":4706,"_vc":95},{"_i":"ms_004803.jpg","_t":4803,"_vc":96},{"_i":"ms_004917.jpg","_t":4917,"_vc":98},{"_i":"ms_005006.jpg","_t":5006,"_vc":98},{"_i":"ms_005124.jpg","_t":5124,"_vc":99},{"_i":"ms_005201.jpg","_t":5201,"_vc":99},{"_i":"ms_005312.jpg","_t":5312,"_vc":99},{"_i":"ms_005400.jpg","_t":5400,"_vc":99},{"_i":"ms_005526.jpg","_t":5526,"_vc":99},{"_i":"ms_005608.jpg","_t":5608,"_vc":99},{"_i":"ms_005715.jpg","_t":5715,"_vc":99},{"_i":"ms_005815.jpg","_t":5815,"_vc":99},{"_i":"ms_005901.jpg","_t":5901,"_vc":100},{"_i":"ms_006000.jpg","_t":6000,"_vc":100},{"_i":"ms_006103.jpg","_t":6103,"_vc":100},{"_i":"ms_006215.jpg","_t":6215,"_vc":100},{"_i":"ms_006308.jpg","_t":6308,"_vc":100},{"_i":"ms_006412.jpg","_t":6412,"_vc":100},{"_i":"ms_006525.jpg","_t":6525,"_vc":100},{"_i":"ms_006628.jpg","_t":6628,"_vc":100},{"_i":"ms_006709.jpg","_t":6709,"_vc":100},{"_i":"ms_006812.jpg","_t":6812,"_vc":99},{"_i":"ms_006919.jpg","_t":6919,"_vc":100},{"_i":"ms_007048.jpg","_t":7048,"_vc":100},{"_i":"ms_007124.jpg","_t":7124,"_vc":100},{"_i":"ms_007267.jpg","_t":7267,"_vc":100},{"_i":"ms_007301.jpg","_t":7301,"_vc":100},{"_i":"ms_007404.jpg","_t":7404,"_vc":100},{"_i":"ms_007542.jpg","_t":7542,"_vc":99},{"_i":"ms_008015.jpg","_t":8015,"_vc":100},{"_i":"ms_008523.jpg","_t":8523,"_vc":100},{"_i":"ms_009004.jpg","_t":9004,"_vc":100},{"_i":"ms_009504.jpg","_t":9504,"_vc":100},{"_i":"ms_010017.jpg","_t":10017,"_vc":99},{"_i":"ms_010508.jpg","_t":10508,"_vc":100},{"_i":"ms_011008.jpg","_t":11008,"_vc":100},{"_i":"ms_011515.jpg","_t":11515,"_vc":100},{"_i":"ms_012013.jpg","_t":12013,"_vc":100},{"_i":"ms_012518.jpg","_t":12518,"_vc":100},{"_i":"ms_013010.jpg","_t":13010,"_vc":100},{"_i":"ms_014003.jpg","_t":14003,"_vc":99},{"_i":"ms_015009.jpg","_t":15009,"_vc":100},{"_i":"ms_016000.jpg","_t":16000,"_vc":100},{"_i":"ms_016356.jpg","_t":16356,"_vc":100}]],"visualComplete":[5701,5716,5901],"lighthouse":[null,45,45],"pagespeed":[71,71,71]}}